ialarmclient/__init__.py
ialarmclient/client.py
ialarmclient/const.py
ialarmclient/log.py
ialarmclient/status.py
ialarmclient/zone.py
ialarmclient_phoenix-1.0.0.dist-info/LICENSE
ialarmclient_phoenix-1.0.0.dist-info/METADATA
ialarmclient_phoenix-1.0.0.dist-info/WHEEL
ialarmclient_phoenix-1.0.0.dist-info/top_level.txt
ialarmclient_phoenix-1.0.0.dist-info/RECORD
