Metadata-Version: 2.1
Name: ialarmclient-phoenix
Version: 1.0.0
Summary: Meiantech, iAlarm, Antifurto365, AllarmiWireless and other alarm systems support
Home-page: https://github.com/phoenix128/python-ialarmclient
Author: Riccardo Tempesta
Author-email: info@riccardotempesta.com
License: UNKNOWN
Platform: UNKNOWN
Classifier: Programming Language :: Python :: 3.7
Classifier: License :: OSI Approved :: MIT License
Classifier: Operating System :: OS Independent
